{
  "HIT_alto": {
    "idx": 586,
    "date": "2016-01-19",
    "y_true": 0.04584147809619565,
    "y_pred": 0.04514581710100174,
    "contributions": [
      [
        "vol_5 > 0.37",
        0.017351706856160328
      ],
      [
        "vol_d > 0.37",
        -0.0032508175635769703
      ],
      [
        "ret_lag_2 > 0.56",
        0.002607099144422374
      ],
      [
        "ret_lag_3 <= -0.53",
        0.002588664973413011
      ],
      [
        "vol_10 > 0.41",
        0.0025852768236462147
      ],
      [
        "vol_w > 0.39",
        -0.002089608948468429
      ],
      [
        "ret_lag_1 <= -0.53",
        0.0017342955457945364
      ],
      [
        "ret_lag_5 > 0.56",
        0.001194921450136493
      ]
    ]
  },
  "FP_sobrepred": {
    "idx": 589,
    "date": "2016-01-22",
    "y_true": 0.007952457773039042,
    "y_pred": 0.025580035522580147,
    "contributions": [
      [
        "vol_5 > 0.37",
        0.017243563730920237
      ],
      [
        "vol_d > 0.37",
        -0.003349741934278452
      ],
      [
        "vol_w > 0.39",
        -0.002504401801590308
      ],
      [
        "-0.02 < ret_lag_3 <= 0.56",
        -0.0023192867608848177
      ],
      [
        "-0.53 < ret_lag_2 <= -0.02",
        -0.0017132237685102021
      ],
      [
        "-0.02 < ret_lag_1 <= 0.56",
        -0.001572439164813869
      ],
      [
        "px_dist_sma_50 <= -0.63",
        0.0013515524321768909
      ],
      [
        "ret_lag_5 > 0.56",
        0.001051630732759176
      ]
    ]
  },
  "FN_subpred": {
    "idx": 584,
    "date": "2016-01-14",
    "y_true": 0.0508381586919132,
    "y_pred": 0.024072906002402306,
    "contributions": [
      [
        "ret_lag_3 > 0.56",
        0.0027895855203106386
      ],
      [
        "ret_lag_2 > 0.56",
        0.0023143402074896637
      ],
      [
        "ret_lag_1 <= -0.53",
        0.0020984216369618774
      ],
      [
        "volume_ratio > 0.34",
        0.0014337144259952105
      ],
      [
        "-0.66 < vol_w <= -0.23",
        0.0014256435266853194
      ],
      [
        "vol_22 <= -0.69",
        -0.0013324278171687324
      ],
      [
        "px_dist_sma_22 <= -0.59",
        0.0012400809664764709
      ],
      [
        "-0.57 < px_dist_sma_10 <= 0.01",
        0.0008511759477633773
      ]
    ]
  }
}